{
  "unversionedId": "content vullen/pdfinbutton",
  "id": "content vullen/pdfinbutton",
  "isDocsHomePage": false,
  "title": "pdfinbutton",
  "description": "",
  "source": "@site/docs/content vullen/pdfinbutton.md",
  "sourceDirName": "content vullen",
  "slug": "/content vullen/pdfinbutton",
  "permalink": "/docs/content vullen/pdfinbutton",
  "editUrl": "https://github.com/DamienVG99/Docusaurus-Pageking/docs/content vullen/pdfinbutton.md",
  "version": "current",
  "sidebarPosition": 6,
  "frontMatter": {
    "sidebar_position": 6
  },
  "sidebar": "tutorialSidebar",
  "previous": {
    "title": "Post Types",
    "permalink": "/docs/content vullen/posttypes"
  },
  "next": {
    "title": "concept",
    "permalink": "/docs/content vullen/concept"
  }
}